diarycli.py
diarycli-0.2.0.dist-info/LICENSE.txt
diarycli-0.2.0.dist-info/METADATA
diarycli-0.2.0.dist-info/WHEEL
diarycli-0.2.0.dist-info/entry_points.txt
diarycli-0.2.0.dist-info/top_level.txt
diarycli-0.2.0.dist-info/RECORD
