Metadata-Version: 2.1
Name: diarycli
Version: 0.2.0
Summary: A CLI program that help creates diary and organize them
Author-email: Rocky Li <aperocky@gmail.com>
License: MIT License
Project-URL: Homepage, https://github.com/Aperocky/diarycli
Project-URL: Source, https://github.com/Aperocky/diarycli
Keywords: diary,cli,vim
License-File: LICENSE.txt
